orpytal/__init__.py
orpytal/base.py
orpytal/errors.py
orpytal/frames.py
orpytal/integration.py
orpytal/maneuvers.py
orpytal/matlab_plotting.py
orpytal/orbit.py
orpytal/output.py
orpytal/planet_constants.py
orpytal/state.py
orpytal/trajectory.py
orpytal/common/__init__.py
orpytal/data/body_data.xml
orpytal/ksp/__init__.py
orpytal/ksp/ksp_planet_constants.py
orpytal/plotting/__init__.py
orpytal/plotting/matlab_plotting.py
orpytal/plotting/mpl_plotting.py
orpytal/plotting/plot_orbits.py
orpytal/plotting/plotly_plotting.py
orpytal/plotting/plotting_base.py
orpytal/plotting/test_plotting.py
orpytal/utils/__init__.py
orpytal/utils/conics_utils.py
orpytal/utils/poliastro_test_utils.py
orpytal/utils/utils.py
orpytal-0.1.0.dist-info/LICENSE
orpytal-0.1.0.dist-info/METADATA
orpytal-0.1.0.dist-info/WHEEL
orpytal-0.1.0.dist-info/top_level.txt
orpytal-0.1.0.dist-info/RECORD
